jarvis_STT/_init_.py
Advance_jarvisGOPIRAJ_STT-0.2.dist-info/METADATA
Advance_jarvisGOPIRAJ_STT-0.2.dist-info/WHEEL
Advance_jarvisGOPIRAJ_STT-0.2.dist-info/top_level.txt
Advance_jarvisGOPIRAJ_STT-0.2.dist-info/RECORD
