Metadata-Version: 2.1
Name: Advance_jarvisGOPIRAJ_STT
Version: 0.2
Summary: this is a speech to text package created by Gopi Raj
Author: Gopi Raj
